testbedutils/Thredds_checker.py
testbedutils/__init__.py
testbedutils/anglesLib.py
testbedutils/cmtbSlack.py
testbedutils/dirtLib.py
testbedutils/fileHandling.py
testbedutils/frfTDSdataCrawler.py
testbedutils/geoprocess.py
testbedutils/gridTools.py
testbedutils/kalman_filter.py
testbedutils/sblib.py
testbedutils/timeDomain.py
testbedutils/waveLib.py
testbedutils-0.1.10.dist-info/METADATA
testbedutils-0.1.10.dist-info/WHEEL
testbedutils-0.1.10.dist-info/top_level.txt
testbedutils-0.1.10.dist-info/RECORD
