Metadata-Version: 2.1
Name: testbedutils
Version: 0.1.10
Summary: Coastal Model Test Bed utilities
Home-page: UNKNOWN
Author: Spicer Bak
Author-email: thesser1@gmail.com
License: UNKNOWN
Platform: UNKNOWN
Requires-Dist: scipy
Requires-Dist: pandas
Requires-Dist: matplotlib
Requires-Dist: numpy
Requires-Dist: utm
Requires-Dist: pyproj
Requires-Dist: python-dateutil
Requires-Dist: netCDF4
Requires-Dist: requests
Requires-Dist: pyyaml
Requires-Dist: slack-sdk
Requires-Dist: progressbar
